{
  "type": "minecraft:crafting_shaped",
  "group": "debris_axe",
  "category": "equipment",
  "pattern": [
    "01",
    "23",
    " 5"
  ],
  "key": {
    "0": {
      "item": "minecraft:netherite_scrap"
    },
    "1": {
      "item": "minecraft:netherite_scrap"
    },
    "2": {
      "item": "minecraft:netherite_scrap"
    },
    "3": {
      "item": "minecraft:quartz"
    },
    "5": {
      "item": "minecraft:quartz"
    }
  },
  "result": {
    "item": "beyond:debris_axe",
    "count": 1
  }
}