{
  "type": "minecraft:crafting_shaped",
  "group": "debris_pickaxe",
  "category": "equipment",
  "pattern": [
    "012",
    " 4 ",
    " 7 "
  ],
  "key": {
    "0": {
      "item": "minecraft:netherite_scrap"
    },
    "1": {
      "item": "minecraft:netherite_scrap"
    },
    "2": {
      "item": "minecraft:netherite_scrap"
    },
    "4": {
      "item": "minecraft:quartz"
    },
    "7": {
      "item": "minecraft:quartz"
    }
  },
  "result": {
    "item": "beyond:debris_pickaxe",
    "count": 1
  }
}